isitdownrightnow/__init__.py
isitdownrightnow/isitdownrightnow.py
isitdownrightnow-0.0.1.dist-info/LICENSE
isitdownrightnow-0.0.1.dist-info/METADATA
isitdownrightnow-0.0.1.dist-info/WHEEL
isitdownrightnow-0.0.1.dist-info/top_level.txt
isitdownrightnow-0.0.1.dist-info/RECORD
