Metadata-Version: 2.1
Name: isitdownrightnow
Version: 0.0.1
Summary: A straightforward wrapper for the IsItDownRightNow API.
Home-page: https://github.com/ccan23/isitdownrightnow
Author: ccan23
Author-email: dev.ccanb@protonmail.com
License: MIT
Keywords: python,uptime,server,website,down,ping
Platform: UNKNOWN
Classifier: Development Status :: 3 - Alpha
Classifier: Intended Audience :: Developers
Classifier: Programming Language :: Python :: 3
Classifier: Operating System :: OS Independent
Classifier: License :: OSI Approved :: MIT License
License-File: LICENSE
Requires-Dist: certifi (==2022.12.7)
Requires-Dist: charset-normalizer (==3.1.0)
Requires-Dist: decorator (==5.1.1)
Requires-Dist: idna (==3.4)
Requires-Dist: lxml (==4.9.2)
Requires-Dist: requests (==2.28.2)
Requires-Dist: urllib3 (==1.26.14)
Requires-Dist: validators (==0.20.0)
